s2u/__init__.py
s2u/s2u.py
s2u-0.3.0.dist-info/LICENSE
s2u-0.3.0.dist-info/METADATA
s2u-0.3.0.dist-info/WHEEL
s2u-0.3.0.dist-info/entry_points.txt
s2u-0.3.0.dist-info/top_level.txt
s2u-0.3.0.dist-info/RECORD
